eyesight_reminder/__init__.py
eyesight_reminder/main.py
eyesight_reminder/resources/icon.png
eyesight_reminder-0.1.0.dist-info/LICENSE
eyesight_reminder-0.1.0.dist-info/METADATA
eyesight_reminder-0.1.0.dist-info/WHEEL
eyesight_reminder-0.1.0.dist-info/entry_points.txt
eyesight_reminder-0.1.0.dist-info/top_level.txt
eyesight_reminder-0.1.0.dist-info/RECORD
