Metadata-Version: 2.2
Name: eyesight-reminder
Version: 0.1.0
Summary: A simple utility to remind you to take regular eye breaks.
Home-page: https://github.com/tjennerjahn/eyesight-reminder
Author: Tobias Jennerjahn
Author-email: tobias@jennerjahn.xyz
License: MIT
Project-URL: Bug Tracker, https://github.com/tjennerjahn/eyesight-reminder/issues
Keywords: eyesight,eye-care,reminder,health,20-20-20,utility
Classifier: Programming Language :: Python :: 3
Classifier: Programming Language :: Python :: 3.8
Classifier: Programming Language :: Python :: 3.9
Classifier: Programming Language :: Python :: 3.10
Classifier: Programming Language :: Python :: 3.11
Classifier: Operating System :: POSIX :: Linux
Classifier: Operating System :: MacOS
Classifier: License :: OSI Approved :: MIT License
Classifier: Topic :: Utilities
Classifier: Intended Audience :: End Users/Desktop
Classifier: Development Status :: 4 - Beta
Requires-Python: >=3.8
License-File: LICENSE
Requires-Dist: PyQt5
Dynamic: author
Dynamic: author-email
Dynamic: classifier
Dynamic: description
Dynamic: description-content-type
Dynamic: home-page
Dynamic: keywords
Dynamic: license
Dynamic: project-url
Dynamic: requires-dist
Dynamic: requires-python
Dynamic: summary
